{"@context":"https://schema.org/","@type":"WebSite","author":{"@id":"http://www.wikidata.org/entity/Q137668638","@type":"Person","name":"Christian Mahnke"},"hasPart":[{"@context":"https://schema.org/","@id":"https://schatten.yaapb.projektemacher.org/","@type":"Blog","author":{"@id":"http://www.wikidata.org/entity/Q137668638","@type":"Person","name":"Christian Mahnke"},"blogPost":[],"mainEntityOfPage":"https://schatten.yaapb.projektemacher.org/","name":"Nocturnal shadows"}],"name":"Nocturnal shadows","url":"https://schatten.yaapb.projektemacher.org/"}